ariana/__init__.py
ariana/bin/ariana-linux-arm64
ariana/bin/ariana-linux-x64
ariana/bin/ariana-macos-arm64
ariana/bin/ariana-macos-x64
ariana/bin/ariana-windows-x64.exe
ariana-0.5.2.dist-info/licenses/LICENCE.txt
ariana-0.5.2.dist-info/METADATA
ariana-0.5.2.dist-info/WHEEL
ariana-0.5.2.dist-info/entry_points.txt
ariana-0.5.2.dist-info/top_level.txt
ariana-0.5.2.dist-info/RECORD
