Metadata-Version: 2.4
Name: ariana
Version: 0.5.2
Summary: Debug your JS/TS/Python code in development way faster than with a traditional debugger
Home-page: https://github.com/dedale-dev/ariana
License: AGPL-3.0-only
License-File: LICENCE.txt
Dynamic: home-page
Dynamic: license
Dynamic: license-file
Dynamic: summary
